{"_id":"husl","_rev":"39-74cbeb5626cd866624ce2b9f54affacb","name":"husl","description":"Human-friendly HSL","dist-tags":{"latest":"6.0.3"},"versions":{"1.0.0":{"name":"husl","description":"Replacement for the HSL color space","keywords":["color","color space","CIE","RGB","stylus","HUSL","HSL"],"version":"1.0.0","author":{"name":"Alexei Boronine","email":"alexei.boronine@gmail.com"},"main":"husl.js","files":["husl.js"],"repository":{"type":"git","url":"git://github.com/boronine/husl.git"},"homepage":"http://boronine.github.com/husl/","_npmUser":{"name":"boronine","email":"alexei.boronine@gmail.com"},"_id":"husl@1.0.0","dependencies":{},"devDependencies":{},"optionalDependencies":{},"engines":{"node":"*"},"_engineSupported":true,"_npmVersion":"1.1.4","_nodeVersion":"v0.6.12","_defaultsLoaded":true,"dist":{"shasum":"e170ebb7e9d8dbb8bdb5d81fd36257a195ac3f8c","tarball":"https://registry.npmjs.org/husl/-/husl-1.0.0.tgz"},"maintainers":[{"name":"boronine","email":"alexei.boronine@gmail.com"}],"directories":{}},"1.0.1":{"name":"husl","description":"Replacement for the HSL color space","keywords":["color","color space","CIE","RGB","stylus","HUSL","HSL"],"version":"1.0.1","author":{"name":"Alexei Boronine","email":"alexei.boronine@gmail.com"},"main":"husl.js","files":["husl.js"],"repository":{"type":"git","url":"git://github.com/boronine/husl.git"},"homepage":"http://boronine.github.com/husl/","_npmUser":{"name":"boronine","email":"alexei.boronine@gmail.com"},"_id":"husl@1.0.1","dependencies":{},"devDependencies":{},"optionalDependencies":{},"engines":{"node":"*"},"_engineSupported":true,"_npmVersion":"1.1.4","_nodeVersion":"v0.6.12","_defaultsLoaded":true,"dist":{"shasum":"8c18fe3c44926c9dbae0ccab97e6104393b0f6ff","tarball":"https://registry.npmjs.org/husl/-/husl-1.0.1.tgz"},"maintainers":[{"name":"boronine","email":"alexei.boronine@gmail.com"}],"directories":{}},"1.0.2":{"name":"husl","description":"Replacement for the HSL color space","keywords":["color","color space","CIE","RGB","stylus","HUSL","HSL"],"version":"1.0.2","author":{"name":"Alexei Boronine","email":"alexei.boronine@gmail.com"},"main":"husl.js","files":["husl.js"],"repository":{"type":"git","url":"git://github.com/boronine/husl.git"},"homepage":"http://boronine.github.com/husl/","_npmUser":{"name":"boronine","email":"alexei.boronine@gmail.com"},"_id":"husl@1.0.2","dependencies":{},"devDependencies":{},"optionalDependencies":{},"engines":{"node":"*"},"_engineSupported":true,"_npmVersion":"1.1.4","_nodeVersion":"v0.6.12","_defaultsLoaded":true,"dist":{"shasum":"93b2c0e506bc8a341afe7a755262c3fd96a1edd1","tarball":"https://registry.npmjs.org/husl/-/husl-1.0.2.tgz"},"maintainers":[{"name":"boronine","email":"alexei.boronine@gmail.com"}],"directories":{}},"2.0.0":{"name":"husl","description":"Replacement for the HSL color space","keywords":["color","color space","CIE","RGB","stylus","HUSL","HSL"],"version":"2.0.0","author":{"name":"Alexei Boronine","email":"alexei.boronine@gmail.com"},"main":"husl.js","files":["husl.js"],"repository":{"type":"git","url":"http://github.com/boronine/husl.git"},"homepage":"http://boronine.github.com/husl/","devDependencies":{"coffee-script":"*","colorspaces":"*","onecolor":"*","png":"*","stylus":"*","eco":"*","mocha":"*","imagediff":"*"},"scripts":{"test":"mocha --compilers coffee:coffee-script"},"_id":"husl@2.0.0","dist":{"shasum":"ace53a4812ed6c43a9a2fcd4862e3ff46f42eecf","tarball":"https://registry.npmjs.org/husl/-/husl-2.0.0.tgz"},"_npmVersion":"1.1.59","_npmUser":{"name":"boronine","email":"alexei.boronine@gmail.com"},"maintainers":[{"name":"boronine","email":"alexei.boronine@gmail.com"}],"directories":{}},"3.0.0":{"name":"husl","description":"Replacement for the HSL color space","keywords":["color","color space","CIE","RGB","stylus","HUSL","HSL"],"version":"3.0.0","author":{"name":"Alexei Boronine","email":"alexei.boronine@gmail.com"},"main":"husl.js","files":["husl.js"],"repository":{"type":"git","url":"http://github.com/boronine/husl.git"},"homepage":"http://boronine.github.com/husl/","devDependencies":{"coffee-script":"*","uglify-js":"*","mocha":"*","stylus":"*"},"scripts":{"test":"mocha --compilers coffee:coffee-script"},"bugs":{"url":"https://github.com/boronine/husl/issues"},"_id":"husl@3.0.0","dist":{"shasum":"48825ca75ec6d96d500d61e10b55c31de444118d","tarball":"https://registry.npmjs.org/husl/-/husl-3.0.0.tgz"},"_from":".","_npmVersion":"1.3.10","_npmUser":{"name":"boronine","email":"alexei.boronine@gmail.com"},"maintainers":[{"name":"boronine","email":"alexei.boronine@gmail.com"}],"directories":{}},"4.0.0":{"name":"husl","description":"Replacement for the HSL color space","keywords":["color","color space","CIE","RGB","stylus","HUSL","HSL"],"version":"4.0.0","author":{"name":"Alexei Boronine","email":"alexei.boronine@gmail.com"},"main":"husl.js","files":["husl.js"],"repository":{"type":"git","url":"http://github.com/boronine/husl.git"},"homepage":"http://www.boronine.com/husl/","devDependencies":{"coffee-script":"*","underscore":"*","uglify-js":"*","mocha":"*","stylus":"*"},"scripts":{"test":"mocha --compilers coffee:coffee-script/register"},"bugs":{"url":"https://github.com/boronine/husl/issues"},"_id":"husl@4.0.0","dist":{"shasum":"3fadc04288677392543000b2af57beca7605a0ca","tarball":"https://registry.npmjs.org/husl/-/husl-4.0.0.tgz"},"_from":".","_npmVersion":"1.4.4","_npmUser":{"name":"boronine","email":"alexei.boronine@gmail.com"},"maintainers":[{"name":"boronine","email":"alexei.boronine@gmail.com"}],"directories":{}},"4.0.1":{"name":"husl","description":"Replacement for the HSL color space","keywords":["color","color space","CIE","RGB","HUSL","HSL"],"version":"4.0.1","author":{"name":"Alexei Boronine","email":"alexei@boronine.com"},"main":"husl.js","files":["husl.js"],"repository":{"type":"git","url":"http://github.com/boronine/husl.git"},"homepage":"http://www.boronine.com/husl/","devDependencies":{"coffee-script":"*","underscore":"*","uglify-js":"*","mocha":"*"},"scripts":{"test":"mocha --compilers coffee:coffee-script/register"},"bugs":{"url":"https://github.com/boronine/husl/issues"},"_id":"husl@4.0.1","dist":{"shasum":"9a355b6f18b6115f3adce0dfa5f14d0d4d84ac2f","tarball":"https://registry.npmjs.org/husl/-/husl-4.0.1.tgz"},"_from":".","_npmVersion":"1.4.4","_npmUser":{"name":"boronine","email":"alexei.boronine@gmail.com"},"maintainers":[{"name":"boronine","email":"alexei.boronine@gmail.com"}],"directories":{}},"4.0.2":{"name":"husl","description":"Replacement for the HSL color space","keywords":["color","color space","CIE","RGB","HUSL","HSL"],"version":"4.0.2","author":{"name":"Alexei Boronine","email":"alexei@boronine.com"},"main":"husl.js","files":["husl.js"],"repository":{"type":"git","url":"http://github.com/boronine/husl.git"},"homepage":"http://www.boronine.com/husl/","devDependencies":{"coffee-script":"*","underscore":"*","uglify-js":"*","mocha":"*"},"scripts":{"test":"mocha --compilers coffee:coffee-script/register"},"bugs":{"url":"https://github.com/boronine/husl/issues"},"_id":"husl@4.0.2","dist":{"shasum":"0495116303ecbca71c19e7f9dc94c129b76efb64","tarball":"https://registry.npmjs.org/husl/-/husl-4.0.2.tgz"},"_from":".","_npmVersion":"1.4.4","_npmUser":{"name":"boronine","email":"alexei.boronine@gmail.com"},"maintainers":[{"name":"boronine","email":"alexei.boronine@gmail.com"}],"directories":{}},"5.0.0":{"name":"husl","description":"Replacement for the HSL color space","keywords":["color","color space","CIE","RGB","HUSL","HSL"],"version":"5.0.0","author":{"name":"Alexei Boronine","email":"alexei@boronine.com"},"main":"husl.js","files":["husl.js"],"repository":{"type":"git","url":"http://github.com/boronine/husl.git"},"homepage":"http://www.boronine.com/husl/","devDependencies":{"coffee-script":"*","underscore":"*","uglify-js":"*","mocha":"*"},"scripts":{"test":"mocha --compilers coffee:coffee-script/register"},"gitHead":"30555091a854645e0c5a01c578e3fe28191883a7","bugs":{"url":"https://github.com/boronine/husl/issues"},"_id":"husl@5.0.0","_shasum":"eb411d583922b4aded14fabaebf5d7fc8a6c8295","_from":".","_npmVersion":"1.4.21","_npmUser":{"name":"boronine","email":"alexei.boronine@gmail.com"},"maintainers":[{"name":"boronine","email":"alexei.boronine@gmail.com"}],"dist":{"shasum":"eb411d583922b4aded14fabaebf5d7fc8a6c8295","tarball":"https://registry.npmjs.org/husl/-/husl-5.0.0.tgz"},"directories":{}},"5.0.1":{"name":"husl","description":"Replacement for the HSL color space","keywords":["color","color space","CIE","RGB","HUSL","HSL"],"version":"5.0.1","author":{"name":"Alexei Boronine","email":"alexei@boronine.com"},"main":"husl.js","files":["husl.js"],"repository":{"type":"git","url":"http://github.com/boronine/husl.git"},"homepage":"http://www.boronine.com/husl/","devDependencies":{"coffee-script":"*","underscore":"*","uglify-js":"*","mocha":"*"},"scripts":{"test":"mocha --compilers coffee:coffee-script/register"},"gitHead":"ee9b89b48c17c704278f7b31f965866059c09492","bugs":{"url":"https://github.com/boronine/husl/issues"},"_id":"husl@5.0.1","_shasum":"e98eef2c522333953f0f7e8361cb8b8da3db267a","_from":".","_npmVersion":"1.4.21","_npmUser":{"name":"boronine","email":"alexei.boronine@gmail.com"},"maintainers":[{"name":"boronine","email":"alexei.boronine@gmail.com"}],"dist":{"shasum":"e98eef2c522333953f0f7e8361cb8b8da3db267a","tarball":"https://registry.npmjs.org/husl/-/husl-5.0.1.tgz"},"directories":{}},"5.0.2":{"name":"husl","description":"Replacement for the HSL color space","keywords":["color","color space","CIE","RGB","HUSL","HSL"],"version":"5.0.2","author":{"name":"Alexei Boronine","email":"alexei@boronine.com"},"main":"husl.js","files":["husl.js"],"repository":{"type":"git","url":"http://github.com/boronine/husl.git"},"homepage":"http://husl.boronine.com/","devDependencies":{"coffee-script":"*","underscore":"*","uglify-js":"*","mocha":"*"},"scripts":{"test":"mocha --compilers coffee:coffee-script/register"},"gitHead":"c54a8b6086c6423f2237bd0cf5cd00441d982aef","bugs":{"url":"https://github.com/boronine/husl/issues"},"_id":"husl@5.0.2","_shasum":"19fbb310b0dd20782971b4bde40b9511a9a3f0c5","_from":".","_npmVersion":"1.4.21","_npmUser":{"name":"boronine","email":"alexei.boronine@gmail.com"},"maintainers":[{"name":"boronine","email":"alexei.boronine@gmail.com"}],"dist":{"shasum":"19fbb310b0dd20782971b4bde40b9511a9a3f0c5","tarball":"https://registry.npmjs.org/husl/-/husl-5.0.2.tgz"},"directories":{}},"5.0.3":{"name":"husl","description":"Replacement for the HSL color space","keywords":["color","color space","CIE","RGB","HUSL","HSL"],"version":"5.0.3","author":{"name":"Alexei Boronine","email":"alexei@boronine.com"},"main":"husl.js","files":["husl.js"],"repository":{"type":"git","url":"http://github.com/husl-colors/husl.git"},"homepage":"http://www.husl-colors.org","devDependencies":{"coffee-script":"*","underscore":"*","uglify-js":"*","mocha":"*"},"scripts":{"test":"mocha --compilers coffee:coffee-script/register"},"gitHead":"9442fd68ac0ba876df59c414c426a1b7ce2807c8","bugs":{"url":"https://github.com/husl-colors/husl/issues"},"_id":"husl@5.0.3","_shasum":"ee272aaff1bebe40df3588ed007b70de7e679788","_from":".","_npmVersion":"1.4.21","_npmUser":{"name":"boronine","email":"alexei.boronine@gmail.com"},"maintainers":[{"name":"boronine","email":"alexei.boronine@gmail.com"}],"dist":{"shasum":"ee272aaff1bebe40df3588ed007b70de7e679788","tarball":"https://registry.npmjs.org/husl/-/husl-5.0.3.tgz"},"directories":{}},"6.0.0":{"name":"husl","description":"Human-friendly HSL","keywords":["color","color space","CIE","RGB","HUSL","HSL"],"version":"6.0.0","author":{"name":"Alexei Boronine","email":"alexei@boronine.com"},"license":"MIT","main":"husl.js","files":["husl.js"],"repository":{"type":"git","url":"git+ssh://git@github.com/husl-colors/husl.git"},"homepage":"http://www.husl-colors.org","devDependencies":{"coffee-script":"*","underscore":"*","uglify-js":"*","mocha":"*"},"scripts":{"test":"mocha --compilers coffee:coffee-script/register"},"gitHead":"a26b60aca3289b35f19db3653f2a19a1c547b609","bugs":{"url":"https://github.com/husl-colors/husl/issues"},"_id":"husl@6.0.0","_shasum":"7e1011b32b7f0c9ae401ba0fc251e3454818f29c","_from":".","_npmVersion":"2.10.1","_nodeVersion":"0.12.4","_npmUser":{"name":"boronine","email":"alexei.boronine@gmail.com"},"dist":{"shasum":"7e1011b32b7f0c9ae401ba0fc251e3454818f29c","tarball":"https://registry.npmjs.org/husl/-/husl-6.0.0.tgz"},"maintainers":[{"name":"boronine","email":"alexei.boronine@gmail.com"}],"directories":{}},"6.0.1":{"name":"husl","description":"Human-friendly HSL","keywords":["color","color space","CIE","RGB","HUSL","HSL"],"version":"6.0.1","author":{"name":"Alexei Boronine","email":"alexei@boronine.com"},"license":"MIT","main":"husl.js","files":["husl.js"],"repository":{"type":"git","url":"git+ssh://git@github.com/husl-colors/husl.git"},"homepage":"http://www.husl-colors.org","devDependencies":{"coffee-script":"*","underscore":"*","uglify-js":"*","mocha":"*"},"scripts":{"test":"mocha --compilers coffee:coffee-script/register"},"gitHead":"a42f3aafa2493aa96fd0b64b1b917688d010a319","bugs":{"url":"https://github.com/husl-colors/husl/issues"},"_id":"husl@6.0.1","_shasum":"c6a9f2edea1fc24c00ccb565903bccf37cf3cc58","_from":".","_npmVersion":"2.10.1","_nodeVersion":"0.12.4","_npmUser":{"name":"boronine","email":"alexei.boronine@gmail.com"},"dist":{"shasum":"c6a9f2edea1fc24c00ccb565903bccf37cf3cc58","tarball":"https://registry.npmjs.org/husl/-/husl-6.0.1.tgz"},"maintainers":[{"name":"boronine","email":"alexei.boronine@gmail.com"}],"directories":{}},"6.0.2-alpha.1":{"name":"husl","description":"Human-friendly HSL","keywords":["color","color space","CIE","RGB","HUSL","HSL"],"version":"6.0.2-alpha.1","author":{"name":"Alexei Boronine","email":"alexei@boronine.com"},"license":"MIT","main":"../dist/husl.min.js","files":["../dist/husl.min.js"],"repository":{"type":"git","url":"git+ssh://git@github.com/husl-colors/husl.git"},"homepage":"http://www.husl-colors.org","bugs":{"url":"https://github.com/husl-colors/husl/issues"},"_id":"husl@6.0.2-alpha.1","scripts":{},"_shasum":"0e5636a4e96756a1f4f1622f24f5e455883e4734","_from":".","_npmVersion":"2.15.9","_nodeVersion":"4.5.0","_npmUser":{"name":"boronine","email":"alexei.boronine@gmail.com"},"dist":{"shasum":"0e5636a4e96756a1f4f1622f24f5e455883e4734","tarball":"https://registry.npmjs.org/husl/-/husl-6.0.2-alpha.1.tgz"},"maintainers":[{"name":"boronine","email":"alexei.boronine@gmail.com"}],"_npmOperationalInternal":{"host":"packages-12-west.internal.npmjs.com","tmp":"tmp/husl-6.0.2-alpha.1.tgz_1479753941612_0.6565175731666386"},"directories":{}},"6.0.2-alpha.2":{"name":"husl","description":"Human-friendly HSL","keywords":["color","color space","CIE","RGB","HUSL","HSL"],"version":"6.0.2-alpha.2","author":{"name":"Alexei Boronine","email":"alexei@boronine.com"},"license":"MIT","main":"dist/husl.min.js","files":["dist/husl.min.js"],"repository":{"type":"git","url":"git+ssh://git@github.com/husl-colors/husl.git"},"homepage":"http://www.husl-colors.org","gitHead":"211786ddb45f054aeb5d6259caecf51609ab0500","bugs":{"url":"https://github.com/husl-colors/husl/issues"},"_id":"husl@6.0.2-alpha.2","scripts":{},"_shasum":"844c7c1021221637f073fdf7fc6096a0a2183952","_from":".","_npmVersion":"2.15.9","_nodeVersion":"4.5.0","_npmUser":{"name":"boronine","email":"alexei.boronine@gmail.com"},"dist":{"shasum":"844c7c1021221637f073fdf7fc6096a0a2183952","tarball":"https://registry.npmjs.org/husl/-/husl-6.0.2-alpha.2.tgz"},"maintainers":[{"name":"boronine","email":"alexei.boronine@gmail.com"}],"_npmOperationalInternal":{"host":"packages-12-west.internal.npmjs.com","tmp":"tmp/husl-6.0.2-alpha.2.tgz_1479754068896_0.41365406732074916"},"directories":{}},"6.0.2-alpha.3":{"name":"husl","description":"Human-friendly HSL","keywords":["color","color space","CIE","RGB","HUSL","HSL"],"version":"6.0.2-alpha.3","author":{"name":"Alexei Boronine","email":"alexei@boronine.com"},"license":"MIT","main":"dist/husl.min.js","files":["dist/husl.min.js"],"repository":{"type":"git","url":"git+ssh://git@github.com/husl-colors/husl.git"},"homepage":"http://www.husl-colors.org","gitHead":"211786ddb45f054aeb5d6259caecf51609ab0500","bugs":{"url":"https://github.com/husl-colors/husl/issues"},"_id":"husl@6.0.2-alpha.3","scripts":{},"_shasum":"154f2e2818184aff89aaa8bfe3f9afaffb38664f","_from":".","_npmVersion":"2.15.9","_nodeVersion":"4.5.0","_npmUser":{"name":"boronine","email":"alexei.boronine@gmail.com"},"dist":{"shasum":"154f2e2818184aff89aaa8bfe3f9afaffb38664f","tarball":"https://registry.npmjs.org/husl/-/husl-6.0.2-alpha.3.tgz"},"maintainers":[{"name":"boronine","email":"alexei.boronine@gmail.com"}],"_npmOperationalInternal":{"host":"packages-12-west.internal.npmjs.com","tmp":"tmp/husl-6.0.2-alpha.3.tgz_1479754398635_0.7193926679901779"},"directories":{}},"6.0.2-alpha.4":{"name":"husl","description":"Human-friendly HSL","keywords":["color","color space","CIE","RGB","HUSL","HSL"],"version":"6.0.2-alpha.4","author":{"name":"Alexei Boronine","email":"alexei@boronine.com"},"license":"MIT","main":"dist/husl.min.js","files":["dist/husl.min.js"],"repository":{"type":"git","url":"git+ssh://git@github.com/husl-colors/husl.git"},"homepage":"http://www.husl-colors.org","bugs":{"url":"https://github.com/husl-colors/husl/issues"},"_id":"husl@6.0.2-alpha.4","scripts":{},"_shasum":"070ead576fd801fe3833126dd243077c94de06b5","_from":".","_npmVersion":"2.15.9","_nodeVersion":"4.5.0","_npmUser":{"name":"boronine","email":"alexei.boronine@gmail.com"},"dist":{"shasum":"070ead576fd801fe3833126dd243077c94de06b5","tarball":"https://registry.npmjs.org/husl/-/husl-6.0.2-alpha.4.tgz"},"maintainers":[{"name":"boronine","email":"alexei.boronine@gmail.com"}],"_npmOperationalInternal":{"host":"packages-12-west.internal.npmjs.com","tmp":"tmp/husl-6.0.2-alpha.4.tgz_1479755227221_0.6007839764934033"},"directories":{}},"6.0.3":{"name":"husl","description":"Human-friendly HSL","keywords":["color","color space","CIE","RGB","HUSL","HSL"],"version":"6.0.3","author":{"name":"Alexei Boronine","email":"alexei@boronine.com"},"license":"MIT","main":"dist/husl.min.js","files":["dist/husl.min.js"],"repository":{"type":"git","url":"git+ssh://git@github.com/husl-colors/husl.git"},"homepage":"http://www.husl-colors.org","bugs":{"url":"https://github.com/husl-colors/husl/issues"},"_id":"husl@6.0.3","scripts":{},"_shasum":"11bd821c95b5e5c7854d012503e7c8134511a744","_from":".","_npmVersion":"2.15.9","_nodeVersion":"4.5.0","_npmUser":{"name":"boronine","email":"alexei.boronine@gmail.com"},"dist":{"shasum":"11bd821c95b5e5c7854d012503e7c8134511a744","tarball":"https://registry.npmjs.org/husl/-/husl-6.0.3.tgz"},"maintainers":[{"name":"boronine","email":"alexei.boronine@gmail.com"}],"_npmOperationalInternal":{"host":"packages-18-east.internal.npmjs.com","tmp":"tmp/husl-6.0.3.tgz_1479755332357_0.8699754446279258"},"directories":{}}},"readme":"# HUSL - JavaScript implementation\n\n## Installation\n\nClient-side: download the latest husl.min.js from the \n[releases page](https://github.com/husl-colors/husl/releases).\n \nOnce this module is loaded in the browser, you can access it via the\nglobal ``window.HUSL``.\n\nServer-side: ``npm install husl``.\n\n## Usage\n\n**husl.toHex(hue, saturation, lightness)**\n\n*hue* is a number between 0 and 360, *saturation* and *lightness* are \nnumbers between 0 and 100. This function returns the resulting color as \na hex string.\n\n**husl.toRGB(hue, saturation, lightness)**\n\nLike above, but returns an array of 3 numbers between 0 and 1, for the \nr, g, and b channel.\n\n**husl.fromHex(hex)**\n\nTakes a hex string and returns the HUSL color as array that contains \nthe hue (0-360), saturation(0-100) and lightness(0-100) channel.\n_Note_: The result can have rounding errors. For example saturation can \nbe 100.00000000000007\n\n**husl.fromRGB(red, green, blue)**\n\nLike above, but *red*, *green* and *blue* are passed as numbers between \n0 and 1.\n\nUse **husl.p.toHex**, **husl.p.toRGB**, **husl.p.fromHex** and \n**husl.p.fromRGB** for the pastel variant (HUSLp). Note that HUSLp does \nnot contain all the colors of RGB, so converting arbitrary RGB to it may \ngenerate invalid HUSLp colors.\n\nHUSL can also be used as a [Stylus](http://learnboost.github.com/stylus/) \nplugin. See [here](https://github.com/husl-colors/husl-stylus).\n\n## Testing\n\n```sh\nnode test.js\n```","maintainers":[{"name":"boronine","email":"alexei.boronine@gmail.com"}],"time":{"modified":"2016-11-21T19:08:54.113Z","created":"2012-05-18T12:57:44.691Z","1.0.0":"2012-05-18T12:57:45.666Z","1.0.1":"2012-05-30T06:23:57.936Z","1.0.2":"2012-06-23T22:40:24.112Z","2.0.0":"2012-09-23T07:41:07.997Z","3.0.0":"2014-01-08T15:49:29.387Z","4.0.0":"2014-04-06T00:37:27.157Z","4.0.1":"2014-07-28T22:05:54.842Z","4.0.2":"2014-07-29T13:12:07.271Z","4.0.3":"2014-09-03T08:48:26.148Z","5.0.0":"2014-09-03T09:20:13.175Z","5.0.1":"2014-10-03T10:09:42.957Z","5.0.2":"2015-01-06T19:19:27.866Z","5.0.3":"2015-04-04T17:57:17.686Z","6.0.0":"2015-06-20T18:59:55.737Z","6.0.1":"2015-09-04T17:59:26.370Z","6.0.2":"2016-11-21T16:44:06.549Z","6.0.2-alpha.1":"2016-11-21T18:45:41.846Z","6.0.2-alpha.2":"2016-11-21T18:47:49.127Z","6.0.2-alpha.3":"2016-11-21T18:53:18.855Z","6.0.2-alpha.4":"2016-11-21T19:07:07.452Z","6.0.3":"2016-11-21T19:08:54.113Z"},"author":{"name":"Alexei Boronine","email":"alexei@boronine.com"},"repository":{"type":"git","url":"git+ssh://git@github.com/husl-colors/husl.git"},"homepage":"http://www.husl-colors.org","keywords":["color","color space","CIE","RGB","HUSL","HSL"],"bugs":{"url":"https://github.com/husl-colors/husl/issues"},"readmeFilename":"README.md","license":"MIT","users":{"darkwark":true,"vorg":true},"_attachments":{},"_etag":"W/\"58334646-54c5\"","_lastModified":"Mon, 21 Nov 2016 19:08:54 GMT"}